[
  { "latitude": 17.385044, "longitude": 78.486671, "timestamp": "2024-07-20T10:00:00Z" },
  { "latitude": 17.3851, "longitude": 78.48675, "timestamp": "2024-07-20T10:00:05Z" },
  { "latitude": 17.3852, "longitude": 78.48685, "timestamp": "2024-07-20T10:00:10Z" },
  { "latitude": 17.3853, "longitude": 78.48695, "timestamp": "2024-07-20T10:00:15Z" },
  { "latitude": 17.3854, "longitude": 78.48705, "timestamp": "2024-07-20T10:00:20Z" },
  { "latitude": 17.3855, "longitude": 78.48715, "timestamp": "2024-07-20T10:00:25Z" },
  { "latitude": 17.3856, "longitude": 78.48725, "timestamp": "2024-07-20T10:00:30Z" },
  { "latitude": 17.3857, "longitude": 78.48735, "timestamp": "2024-07-20T10:00:35Z" },
  { "latitude": 17.3858, "longitude": 78.48745, "timestamp": "2024-07-20T10:00:40Z" },
  { "latitude": 17.3859, "longitude": 78.48755, "timestamp": "2024-07-20T10:00:45Z" },
  { "latitude": 17.386, "longitude": 78.48765, "timestamp": "2024-07-20T10:00:50Z" },
  { "latitude": 17.3861, "longitude": 78.48775, "timestamp": "2024-07-20T10:00:55Z" },
  { "latitude": 17.3862, "longitude": 78.48785, "timestamp": "2024-07-20T10:01:00Z" },
  { "latitude": 17.3863, "longitude": 78.48795, "timestamp": "2024-07-20T10:01:05Z" },
  { "latitude": 17.3864, "longitude": 78.48805, "timestamp": "2024-07-20T10:01:10Z" },
  { "latitude": 17.3865, "longitude": 78.48815, "timestamp": "2024-07-20T10:01:15Z" },
  { "latitude": 17.3866, "longitude": 78.48825, "timestamp": "2024-07-20T10:01:20Z" },
  { "latitude": 17.3867, "longitude": 78.48835, "timestamp": "2024-07-20T10:01:25Z" },
  { "latitude": 17.3868, "longitude": 78.48845, "timestamp": "2024-07-20T10:01:30Z" },
  { "latitude": 17.3869, "longitude": 78.48855, "timestamp": "2024-07-20T10:01:35Z" },
  { "latitude": 17.387, "longitude": 78.48865, "timestamp": "2024-07-20T10:01:40Z" },
  { "latitude": 17.3871, "longitude": 78.48875, "timestamp": "2024-07-20T10:01:45Z" },
  { "latitude": 17.3872, "longitude": 78.48885, "timestamp": "2024-07-20T10:01:50Z" },
  { "latitude": 17.3873, "longitude": 78.48895, "timestamp": "2024-07-20T10:01:55Z" },
  { "latitude": 17.3874, "longitude": 78.48905, "timestamp": "2024-07-20T10:02:00Z" },
  { "latitude": 17.3875, "longitude": 78.48915, "timestamp": "2024-07-20T10:02:05Z" },
  { "latitude": 17.3876, "longitude": 78.48925, "timestamp": "2024-07-20T10:02:10Z" },
  { "latitude": 17.3877, "longitude": 78.48935, "timestamp": "2024-07-20T10:02:15Z" },
  { "latitude": 17.3878, "longitude": 78.48945, "timestamp": "2024-07-20T10:02:20Z" },
  { "latitude": 17.3879, "longitude": 78.48955, "timestamp": "2024-07-20T10:02:25Z" },
  { "latitude": 17.388, "longitude": 78.48965, "timestamp": "2024-07-20T10:02:30Z" },
  { "latitude": 17.3881, "longitude": 78.48975, "timestamp": "2024-07-20T10:02:35Z" },
  { "latitude": 17.3882, "longitude": 78.48985, "timestamp": "2024-07-20T10:02:40Z" },
  { "latitude": 17.3883, "longitude": 78.48995, "timestamp": "2024-07-20T10:02:45Z" },
  { "latitude": 17.3884, "longitude": 78.49005, "timestamp": "2024-07-20T10:02:50Z" },
  { "latitude": 17.3885, "longitude": 78.49015, "timestamp": "2024-07-20T10:02:55Z" },
  { "latitude": 17.3886, "longitude": 78.49025, "timestamp": "2024-07-20T10:03:00Z" },
  { "latitude": 17.3887, "longitude": 78.49035, "timestamp": "2024-07-20T10:03:05Z" },
  { "latitude": 17.3888, "longitude": 78.49045, "timestamp": "2024-07-20T10:03:10Z" },
  { "latitude": 17.3889, "longitude": 78.49055, "timestamp": "2024-07-20T10:03:15Z" },
  { "latitude": 17.389, "longitude": 78.49065, "timestamp": "2024-07-20T10:03:20Z" },
  { "latitude": 17.3891, "longitude": 78.49075, "timestamp": "2024-07-20T10:03:25Z" },
  { "latitude": 17.3892, "longitude": 78.49085, "timestamp": "2024-07-20T10:03:30Z" },
  { "latitude": 17.3893, "longitude": 78.49095, "timestamp": "2024-07-20T10:03:35Z" },
  { "latitude": 17.3894, "longitude": 78.49105, "timestamp": "2024-07-20T10:03:40Z" },
  { "latitude": 17.3895, "longitude": 78.49115, "timestamp": "2024-07-20T10:03:45Z" },
  { "latitude": 17.3896, "longitude": 78.49125, "timestamp": "2024-07-20T10:03:50Z" },
  { "latitude": 17.3897, "longitude": 78.49135, "timestamp": "2024-07-20T10:03:55Z" },
  { "latitude": 17.3898, "longitude": 78.49145, "timestamp": "2024-07-20T10:04:00Z" },
  { "latitude": 17.3899, "longitude": 78.49155, "timestamp": "2024-07-20T10:04:05Z" },
  { "latitude": 17.39, "longitude": 78.49165, "timestamp": "2024-07-20T10:04:10Z" },
  { "latitude": 17.3901, "longitude": 78.49175, "timestamp": "2024-07-20T10:04:15Z" },
  { "latitude": 17.3902, "longitude": 78.49185, "timestamp": "2024-07-20T10:04:20Z" },
  { "latitude": 17.3903, "longitude": 78.49195, "timestamp": "2024-07-20T10:04:25Z" },
  { "latitude": 17.3904, "longitude": 78.49205, "timestamp": "2024-07-20T10:04:30Z" },
  { "latitude": 17.3905, "longitude": 78.49215, "timestamp": "2024-07-20T10:04:35Z" },
  { "latitude": 17.3906, "longitude": 78.49225, "timestamp": "2024-07-20T10:04:40Z" },
  { "latitude": 17.3907, "longitude": 78.49235, "timestamp": "2024-07-20T10:04:45Z" },
  { "latitude": 17.3908, "longitude": 78.49245, "timestamp": "2024-07-20T10:04:50Z" },
  { "latitude": 17.3909, "longitude": 78.49255, "timestamp": "2024-07-20T10:04:55Z" },
  { "latitude": 17.391, "longitude": 78.49265, "timestamp": "2024-07-20T10:05:00Z" }
]
